{
  "content": [
    {
      "content": null,
      "created": "2024-11-02T09:55:17.979016Z",
      "format": null,
      "hash": null,
      "hash_algorithm": null,
      "last_modified": "2024-11-02T09:55:15.514986Z",
      "mimetype": "application/json",
      "name": "data.json",
      "path": "data.json",
      "size": 61060,
      "type": "file",
      "writable": true
    },
    {
      "content": null,
      "created": "2024-11-02T09:55:17.983016Z",
      "format": null,
      "hash": null,
      "hash_algorithm": null,
      "last_modified": "2024-11-02T09:55:15.514986Z",
      "mimetype": "application/json",
      "name": "ticker2.json",
      "path": "ticker2.json",
      "size": 6009,
      "type": "file",
      "writable": true
    },
    {
      "content": null,
      "created": "2024-11-02T09:55:17.979016Z",
      "format": null,
      "hash": null,
      "hash_algorithm": null,
      "last_modified": "2024-11-02T09:55:15.514986Z",
      "mimetype": "application/json",
      "name": "beam.json",
      "path": "beam.json",
      "size": 3422,
      "type": "file",
      "writable": true
    }
  ],
  "created": "2024-11-02T09:55:17.983016Z",
  "format": "json",
  "hash": null,
  "hash_algorithm": null,
  "last_modified": "2024-11-02T09:55:17.983016Z",
  "mimetype": null,
  "name": "",
  "path": "",
  "size": null,
  "type": "directory",
  "writable": true
}